{
  "lisaManagerReferenceNumber" : "Z543210",
  "lisaProviderName" : "Example Building Society",
  "_links" :
  {
    "self" : {"href" : "/lifetime-isa/manager/{LISAManagerReferenceNumber}"},
    "investors" : {"href" : "/lifetime-isa/manager/{lisaManagerReferenceNumber}/investors"},
    "accounts" : {"href" : " /lifetime-isa/manager/{lisaManagerReferenceNumber}/accounts"},
    "update Account" : {"href" : " /lifetime-isa/manager/{lisaManagerReferenceNumber}/accounts/{accountID}"},
    "life events" : {"href" : " /lifetime-isa/manager/{lisaManagerReferenceNumber}/accounts/{accountID}/events"},
    "transactions" : {"href" : " /lifetime-isa/manager/{lisaManagerReferenceNumber}/accounts/{accountID}/transactions"}
  }
}
